ADDU/__init__.py
ADDU/main.py
ADDU/cli/__init__.py
ADDU/cli/addu.py
ADDU/cli/addu_panels.py
ADDU/config/__init__.py
ADDU/config/config.yaml
ADDU/logic/__init__.py
ADDU/logic/actions.py
ADDU/logic/docker_snippets.py
ADDU/logic/workspace.py
addu-1.1.1.dist-info/METADATA
addu-1.1.1.dist-info/WHEEL
addu-1.1.1.dist-info/entry_points.txt
addu-1.1.1.dist-info/top_level.txt
addu-1.1.1.dist-info/RECORD
