Metadata-Version: 2.1
Name: addu
Version: 1.1.1
Summary: ADDU is a cli tool for creating and managing Dockerized ROS Environments
Home-page: https://github.com/Daiego43/ADDU
Author: Diego Delgado Chaves
Author-email: diedelcha@gmail.com
Classifier: Programming Language :: Python :: 3.10
Classifier: Operating System :: POSIX :: Linux
Requires-Python: >=3.10
Requires-Dist: certifi >=2024.2.2
Requires-Dist: charset-normalizer >=3.3.2
Requires-Dist: docker >=7.0.0
Requires-Dist: idna >=3.6
Requires-Dist: markdown-it-py >=3.0.0
Requires-Dist: mdurl >=0.1.2
Requires-Dist: packaging >=23.2
Requires-Dist: Pygments >=2.17.2
Requires-Dist: PyYAML >=6.0.1
Requires-Dist: requests >=2.31.0
Requires-Dist: rich >=13.7.0
Requires-Dist: urllib3 >=2.2.0
